LICENSE
MANIFEST.in
README
setup.py
whizzer/__init__.py
whizzer/client.py
whizzer/debug.py
whizzer/defer.py
whizzer/process.py
whizzer/protocol.py
whizzer/server.py
whizzer/transport.py
whizzer.egg-info/PKG-INFO
whizzer.egg-info/SOURCES.txt
whizzer.egg-info/dependency_links.txt
whizzer.egg-info/requires.txt
whizzer.egg-info/top_level.txt
whizzer/rpc/__init__.py
whizzer/rpc/dispatch.py
whizzer/rpc/msgpackrpc.py
whizzer/rpc/picklerpc.py
whizzer/rpc/proxy.py
whizzer/rpc/service.py
whizzer/test/__init__.py
whizzer/test/common.py
whizzer/test/mocks.py
whizzer/test/test_client.py
whizzer/test/test_defer.py
whizzer/test/test_process.py
whizzer/test/test_protocol.py
whizzer/test/test_rpc_msgpack.py
whizzer/test/test_rpc_pickle.py
whizzer/test/test_server.py
whizzer/test/test_transport.py