Metadata-Version: 1.0
Name: whizzer
Version: 0.4.0
Summary: Fast event driven socket server framework based on pyev
Home-page: http://github.com/bfrog/whizzer
Author: Tom Burdick
Author-email: thomas.burdick@gmail.com
License: UNKNOWN
Platform: UNKNOWN
Classifier: Intended Audience :: Developers
Classifier: License :: OSI Approved :: MIT License
Classifier: Programming Language :: Python
Classifier: Programming Language :: Python :: 2
Classifier: Programming Language :: Python :: 3
Classifier: Topic :: Software Development :: Libraries :: Python Modules
Classifier: Topic :: System :: Networking
Classifier: Topic :: Internet
